morphology_workflows/__init__.py
morphology_workflows/annotation.py
morphology_workflows/clone.py
morphology_workflows/curation.py
morphology_workflows/marker_helper.py
morphology_workflows/placeholders.py
morphology_workflows/repair.py
morphology_workflows/transform.py
morphology_workflows/utils.py
morphology_workflows/_data/default_placeholders.csv
morphology_workflows/_templates/allen_config.json
morphology_workflows/_templates/logging.conf
morphology_workflows/_templates/luigi.cfg
morphology_workflows/_templates/mouselight_config.json
morphology_workflows/_templates/neuromorpho_config.json
morphology_workflows/_templates/placeholder_config_schema.json
morphology_workflows/_templates/config_templates/default.cfg
morphology_workflows/_templates/config_templates/example_template_curate_dataset.cfg
morphology_workflows/_templates/source_report/conf.py
morphology_workflows/tasks/__init__.py
morphology_workflows/tasks/annotation.py
morphology_workflows/tasks/cli.py
morphology_workflows/tasks/clone.py
morphology_workflows/tasks/curation.py
morphology_workflows/tasks/fetch.py
morphology_workflows/tasks/placeholders.py
morphology_workflows/tasks/repair.py
morphology_workflows/tasks/transform.py
morphology_workflows/tasks/workflows.py
morphology_workflows-0.12.1.dist-info/AUTHORS.md
morphology_workflows-0.12.1.dist-info/LICENSE.txt
morphology_workflows-0.12.1.dist-info/METADATA
morphology_workflows-0.12.1.dist-info/WHEEL
morphology_workflows-0.12.1.dist-info/entry_points.txt
morphology_workflows-0.12.1.dist-info/top_level.txt
morphology_workflows-0.12.1.dist-info/RECORD
