Metadata-Version: 2.1
Name: morphology-workflows
Version: 0.12.1
Summary: Workflows used for morphology processing.
Home-page: https://morphology-workflows.readthedocs.io
Author: Blue Brain Project, EPFL
License: Apache License 2.0
Project-URL: Tracker, https://github.com/BlueBrain/morphology-workflows/issues
Project-URL: Source, https://github.com/BlueBrain/morphology-workflows
Classifier: Development Status :: 4 - Beta
Classifier: Intended Audience :: Education
Classifier: Intended Audience :: Science/Research
Classifier: License :: OSI Approved :: Apache Software License
Classifier: Programming Language :: Python
Classifier: Programming Language :: Python :: 3
Classifier: Programming Language :: Python :: 3.10
Classifier: Programming Language :: Python :: 3.11
Classifier: Programming Language :: Python :: 3.12
Classifier: Topic :: Scientific/Engineering :: Bio-Informatics
Requires-Python: >=3.10
License-File: LICENSE.txt
License-File: AUTHORS.md
Requires-Dist: data-validation-framework >=0.7.0
Requires-Dist: diameter-synthesis <0.6,>=0.5.2
Requires-Dist: luigi >=3.2
Requires-Dist: luigi-tools >=0.3.3
Requires-Dist: matplotlib >=3.4
Requires-Dist: morphapi >=0.3
Requires-Dist: morph-tool <3.0,>=2.11.2
Requires-Dist: morphio <4.0,>=3.3.6
Requires-Dist: neurom <4.0,>=3.2.10
Requires-Dist: neuror <2.0,>=1.6.3
Requires-Dist: numpy >=1.23
Requires-Dist: pandas >=1.5
Requires-Dist: plotly-helper <1.0,>=0.0.8
Requires-Dist: PyYAML >=6
Requires-Dist: rst2pdf >=0.99
Requires-Dist: scipy >=1.8
Requires-Dist: tqdm >=4.44
Requires-Dist: bluepyparallel >=0.2.2
Requires-Dist: lxml >=4.8
Requires-Dist: neuroc <1.0,>=0.3.0
Requires-Dist: seaborn >=0.11
Requires-Dist: urllib3 <2,>=1.26 ; python_version < "3.9"
Provides-Extra: docs
Requires-Dist: docutils <0.21 ; extra == 'docs'
Requires-Dist: graphviz ; extra == 'docs'
Requires-Dist: m2r2 ; extra == 'docs'
Requires-Dist: sphinx-argparse ; extra == 'docs'
Requires-Dist: sphinx-autoapi ; extra == 'docs'
Requires-Dist: sphinx-bluebrain-theme ; extra == 'docs'
Requires-Dist: sphinx-jsonschema ; extra == 'docs'
Provides-Extra: graphviz
Requires-Dist: graphviz ; extra == 'graphviz'
Provides-Extra: mouselight
Requires-Dist: brainglobe-atlasapi >=2 ; extra == 'mouselight'
Provides-Extra: test
Requires-Dist: dictdiffer >=0.8 ; extra == 'test'
Requires-Dist: diff-pdf-visually >=1.7 ; extra == 'test'
Requires-Dist: dir-content-diff >=1.10 ; extra == 'test'
Requires-Dist: morph-tool <3.0,>=2.11.1 ; extra == 'test'
Requires-Dist: pytest >=7 ; extra == 'test'
Requires-Dist: pytest-console-scripts >=1.4 ; extra == 'test'
Requires-Dist: pytest-cov >=4.1 ; extra == 'test'
Requires-Dist: pytest-html >=3.2 ; extra == 'test'
Requires-Dist: pytest-xdist >=2 ; extra == 'test'
